repocoder/__init__.py
repocoder/main.py
repocoder-0.1.15.dist-info/LICENSE.md
repocoder-0.1.15.dist-info/METADATA
repocoder-0.1.15.dist-info/WHEEL
repocoder-0.1.15.dist-info/top_level.txt
repocoder-0.1.15.dist-info/RECORD
