Metadata-Version: 2.1
Name: repocoder
Version: 0.1.15
Summary: A tool for analyzing and modifying code repositories using LLMs
Home-page: https://github.com/jroakes/repocoder
Author: JR Oakes
Author-email: jroakes@gmail.com
Classifier: Development Status :: 3 - Alpha
Classifier: Intended Audience :: Developers
Classifier: License :: OSI Approved :: MIT License
Classifier: Operating System :: OS Independent
Classifier: Programming Language :: Python :: 3
Classifier: Programming Language :: Python :: 3.7
Classifier: Programming Language :: Python :: 3.8
Classifier: Programming Language :: Python :: 3.9
Classifier: Programming Language :: Python :: 3.10
Requires-Python: >=3.7
License-File: LICENSE.md
Requires-Dist: google-generativeai
Requires-Dist: python-dotenv
Requires-Dist: anthropic
Requires-Dist: chardet
